codecli/__init__.py
codecli/apic.py
codecli/utils.py
codecli/commands/__init__.py
codecli/commands/clone.py
codecli/commands/config.py
codecli/commands/end.py
codecli/commands/fetch.py
codecli/commands/fork.py
codecli/commands/hotfix.py
codecli/commands/merge.py
codecli/commands/pullreq.py
codecli/commands/start.py
codecli/commands/sync.py
codecli/providers/__init__.py
codecli/providers/base.py
codecli/providers/provider_code.py
codecli/providers/provider_github.py
CodeCLI-0.1.dist-info/DESCRIPTION.rst
CodeCLI-0.1.dist-info/entry_points.txt
CodeCLI-0.1.dist-info/METADATA
CodeCLI-0.1.dist-info/metadata.json
CodeCLI-0.1.dist-info/RECORD
CodeCLI-0.1.dist-info/top_level.txt
CodeCLI-0.1.dist-info/WHEEL
