Metadata-Version: 2.0
Name: CodeCLI
Version: 0.1
Summary: A command line tool for CODE
Home-page: UNKNOWN
Author: Qiangning Hong
Author-email: hongqn@gmail.com
License: BSD
Platform: UNKNOWN
